MANIFEST.in
README.rst
setup.py
analysis/__init__.py
analysis/admin.py
analysis/db.py
analysis/middleware.py
analysis/models.py
analysis/tests.py
analysis/urls.py
analysis/views.py
analysis/templates/analysis/index.html
django_analysis.egg-info/PKG-INFO
django_analysis.egg-info/SOURCES.txt
django_analysis.egg-info/dependency_links.txt
django_analysis.egg-info/top_level.txt