Metadata-Version: 1.0
Name: django-analysis
Version: 0.2
Summary: A analysis tool for django app.
Home-page: https://github.com/Yooke/django-analysis
Author: Em Lei
Author-email: live1989@foxmail.com
License: BSD License
Platform: UNKNOWN
